{
  "id": "Himnario Adventista Jesús regresará pronto",
  "title": "Himnario Adventista Jesús regresará pronto",
  "_type": "playlist",
  "entries": [
    {
      "_type": "url",
      "ie_key": "Youtube",
      "id": "MCrw0DlLyn0",
      "url": "https://www.youtube.com/watch?v=MCrw0DlLyn0",
      "title": "HA62 | Himno 170 | Jesús pronto volverá",
      "description": "al mundo con gran poder.",
      "duration": 155,
      "channel_id": "UC2TQFq0vEPs1xn-T70FmoTQ",
      "channel": "Himnario adventista 62",
      "channel_url": "https://www.youtube.com/channel/UC2TQFq0vEPs1xn-T70FmoTQ",
      "uploader": "Himnario adventista 62",
      "uploader_id": "@himnarioHA62",
      "uploader_url": "https://www.youtube.com/@himnarioHA62",
      "thumbnails": [
        {
          "url": "https://i.ytimg.com/vi/MCrw0DlLyn0/hqdefault.jpg?sqp=-oaymwEfCOADEI4CSFXyq4qpAxEIARUAAIhCGAFwAcABBrgCGKLzl_8DCgjvgfzQBRjgqAE=&rs=AOn4CLCwG8XcnSQNfnnDprye_wvEgSI8RA&usqp=CBg",
          "height": 270,
          "width": 480
        }
      ],
      "timestamp": null,
      "release_timestamp": null,
      "availability": null,
      "view_count": 8090244,
      "live_status": null,
      "channel_is_verified": null,
      "__x_forwarded_for_ip": null
    }
  ],
  "webpage_url": "ytsearch1:Himnario Adventista Jesús regresará pronto",
  "original_url": "ytsearch1:Himnario Adventista Jesús regresará pronto",
  "webpage_url_basename": "Himnario Adventista Jesús regresará pronto",
  "webpage_url_domain": null,
  "extractor": "youtube:search",
  "extractor_key": "YoutubeSearch",
  "release_year": null,
  "playlist_count": 1,
  "epoch": 1784755054,
  "__files_to_move": {},
  "_version": {
    "version": "2026.07.04",
    "current_git_head": null,
    "release_git_head": "997fa140840a08df3938b40da470c78049fef1f6",
    "repository": "yt-dlp/yt-dlp"
  },
  "videos": [
    {
      "url": "https://www.youtube.com/watch?v=JWUNq6Kt1j4",
      "title": "164 - Jesús pronto volverá | Himnario Adventista | Letra Oficial | 4K60fps"
    },
    {
      "url": "https://www.youtube.com/watch?v=s6_Z-YCuHYE",
      "title": "El Regreso Del Señor: Jesús Regresará Pronto I Jentezen Franklin"
    },
    {
      "url": "https://www.youtube.com/watch?v=MCrw0DlLyn0",
      "title": "HA62 | Himno 170 | Jesús pronto volverá"
    }
  ]
}