{
  "title": "58 - Quiero hacer lo que Tú quieras, Señor",
  "author": "",
  "speed": 1,
  "verses": [],
  "coro": [],
  "audioFilters": {
    "gain": 1,
    "bass": 0,
    "mid": 0,
    "treble": 0
  },
  "introducao": 0,
  "videos": [
    {
      "url": "https://www.youtube.com/watch?v=tqpEiJbVk2k",
      "title": "Himno Adventista 524 - Traían en silencio presentes al Señor"
    },
    {
      "url": "https://www.youtube.com/watch?v=wwT6NslUwRY",
      "title": "Haz lo que quieras de mi Señor...Himno con letra"
    },
    {
      "url": "https://www.youtube.com/watch?v=LM_oYKtphxQ",
      "title": "YO QUIERO LO QUE QUIERAS TÚ   SM"
    }
  ]
}
