{
  "title": "62 - Cara a cara",
  "author": "",
  "speed": 1,
  "verses": [],
  "coro": [],
  "audioFilters": {
    "gain": 1,
    "bass": 0,
    "mid": 0,
    "treble": 0
  },
  "introducao": 0,
  "videos": [
    {
      "url": "https://www.youtube.com/watch?v=xsSWHLZ1tbI",
      "title": "CARA A CARA l HIMNOS Y COROS l BETHEL TELEVISIÓN"
    },
    {
      "url": "https://www.youtube.com/watch?v=LnS6z-kfmyU",
      "title": "Cara a Cara Himno Página 57 | Ministerio Gloria Celestial"
    },
    {
      "url": "https://www.youtube.com/watch?v=KpbL1sR4EHE",
      "title": "Cara a cara espero verle"
    }
  ]
}
