{
  "title": "106 - Mi Redentor",
  "author": "",
  "speed": 1,
  "verses": [],
  "coro": [],
  "audioFilters": {
    "gain": 1,
    "bass": 0,
    "mid": 0,
    "treble": 0
  },
  "introducao": 0,
  "videos": [
    {
      "url": "https://www.youtube.com/watch?v=WVa_hjg_LQQ",
      "title": "Himno 407 - Muy cerca de mi Redentor | Nuevo"
    },
    {
      "url": "https://www.youtube.com/watch?v=S9pkry-s8h0",
      "title": "Himno 304 - Mi Redentor, el rey de gloria | Nuevo"
    },
    {
      "url": "https://www.youtube.com/watch?v=MzLTLxNCR40",
      "title": "Himno 373 - Mi Redentor es Cristo | Nuevo"
    }
  ]
}
