{
  "title": "107 - Milicia de Jesús",
  "author": "",
  "speed": 1,
  "verses": [],
  "coro": [],
  "audioFilters": {
    "gain": 1,
    "bass": 0,
    "mid": 0,
    "treble": 0
  },
  "introducao": 0,
  "videos": [
    {
      "url": "https://www.youtube.com/watch?v=R1zKaMphf50",
      "title": "LA MILICIA DE JESÚS | PR. FITO GÓMEZ | IGLESIA ENCUENTRO PODEROSO"
    },
    {
      "url": "https://www.youtube.com/watch?v=pVtnHg66OPA",
      "title": "OLIVIA, MARISELA E INGRID DE GRUPO MILICIA DE JESÚS Y DE MARÍA | ALIADOS CONTRA LAS ADICCIONES"
    },
    {
      "url": "https://www.youtube.com/watch?v=4WZ4hCQ54dw",
      "title": "Acepta El Perdón De Jesús - Himnos de Gloria 29"
    }
  ]
}
