{
  "title": "125 - El gran amor",
  "author": "",
  "speed": 1,
  "verses": [],
  "coro": [],
  "audioFilters": {
    "gain": 1,
    "bass": 0,
    "mid": 0,
    "treble": 0
  },
  "introducao": 0,
  "videos": [
    {
      "url": "https://www.youtube.com/watch?v=1Vnsj20-AlA",
      "title": "Canto el gran amor - Himno 107 | Nuevo"
    },
    {
      "url": "https://www.youtube.com/watch?v=RtjZkvbqpp8",
      "title": "HIMNO 107 - CANTO EL GRAN AMOR | Nuevo"
    },
    {
      "url": "https://www.youtube.com/watch?v=JCL76ysrB-s",
      "title": "Canto el gran amor | Himno Adventista 107  | Versión renovada"
    }
  ]
}
