{
  "title": "189 - Ven a Cristo",
  "author": "",
  "speed": 1,
  "verses": [],
  "coro": [],
  "audioFilters": {
    "gain": 1,
    "bass": 0,
    "mid": 0,
    "treble": 0
  },
  "introducao": 0,
  "videos": [
    {
      "url": "https://www.youtube.com/watch?v=F93uC8htD_E",
      "title": "HA62 | Himno 126 | Ven a Cristo"
    },
    {
      "url": "https://www.youtube.com/watch?v=OjmA-XlCfmA",
      "title": "Vem a Cristo! - Hinário Evangélico 217"
    },
    {
      "url": "https://www.youtube.com/watch?v=4itUZyxpYJQ",
      "title": "Jovens Lutadores - Hinos e Cânticos 404"
    }
  ]
}
