{
  "title": "169 - Seguirei a Cristo",
  "author": "Henry Maxwell Wright",
  "speed": 1,
  "verses": [
    [
      "1. Sempre! Sempre! Seguirei a Cristo!",
      "Onde quer que Ele for, O seguirei,",
      "Sempre! Sempre! Seguirei a Cristo!",
      "Onde quer que Ele for, O seguirei!"
    ]
  ],
  "audioFilters": {
    "gain": 1.2,
    "bass": 0,
    "mid": -5,
    "treble": 12
  },
  "introducao": 0,
  "videos": [
    {
      "url": "https://www.youtube.com/watch?v=Tlz7aU1XIMI",
      "title": "SEGUIREI A CRISTO - 452. HARPA CRISTÃ- (CIFRADO) - Carlos josé"
    },
    {
      "url": "https://www.youtube.com/watch?v=8YAp95jm9DA",
      "title": "Seguirei a Cristo"
    },
    {
      "url": "https://www.youtube.com/watch?v=OjmA-XlCfmA",
      "title": "Vem a Cristo! - Hinário Evangélico 217"
    }
  ]
}